idanalyzer/__init__.py
idanalyzer/idanalyzer.py
idanalyzer-1.2.2.dist-info/LICENSE
idanalyzer-1.2.2.dist-info/METADATA
idanalyzer-1.2.2.dist-info/WHEEL
idanalyzer-1.2.2.dist-info/top_level.txt
idanalyzer-1.2.2.dist-info/RECORD
