Metadata-Version: 2.1
Name: idanalyzer
Version: 1.2.2
Summary: ID Analyzer API client library, scan and verify global passport, driver license and identification card.
Home-page: https://www.idanalyzer.com
Author: ID Analyzer
Author-email: <support@idanalyzer.com>
License: MIT
Keywords: id card,driver license,passport,id verification,identification card,identity document,mrz,pdf417,aamva,aml,pep,sign document
Platform: UNKNOWN
Classifier: Development Status :: 5 - Production/Stable
Classifier: Intended Audience :: Information Technology
Classifier: Intended Audience :: Financial and Insurance Industry
Classifier: Intended Audience :: Telecommunications Industry
Classifier: Programming Language :: Python :: 2
Classifier: Programming Language :: Python :: 3
Classifier: License :: OSI Approved :: MIT License
Classifier: Topic :: Security
Classifier: Operating System :: OS Independent
Requires-Dist: requests
